{
  "file_data": [
    {
      "desc": {
        "cause": "Planned Maintenance",
        "cluster": false,
        "cust_a": {
          "val": 801
        },
        "etr": "2020-12-10T14:00:00-0400",
        "start": "2020-12-10T09:19:10-0400"
      },
      "geom": {
        "a": [
          "shfyGbrtnJg_@jlAskArdB_|@xd@aI`D}bBe@yi@qb@pNeZvmC_}BjcD}^"
        ],
        "p": [
          "sikyG|ixnJ"
        ]
      },
      "id": "5",
      "title": "Outage Information"
    }
  ],
  "file_title": "030321"
}
