{
  "file_data": [
    {
      "desc": {
        "cause": "High Winds",
        "cluster": false,
        "cust_a": {
          "val": 101
        },
        "etr": "2020-12-26T09:15:00-0400",
        "start": "2020-12-26T01:05:30-0400"
      },
      "geom": {
        "a": [
          "ewauG`i{{J{i@t{KgDvl@}yA|qBqd@{mDhPebH|{@ujJrf@dtAvy@djD"
        ],
        "p": [
          "isduGd{`|J"
        ]
      },
      "id": "5",
      "title": "Outage Information"
    }
  ],
  "file_title": "030320"
}
